{
  "mode": "structure",
  "spacegroup": [
    "Cmc2_1",
    36
  ],
  "bravais_lattice": "oC",
  "bravais_lattice_extended": "oC2",
  "input_lattice_A": [
    [
      5.20783,
      0.0,
      0.0
    ],
    [
      0.0,
      5.20783,
      0.0
    ],
    [
      0.0,
      0.0,
      19.13706
    ]
  ],
  "input_reciprocal_lattice_Ainv_2pi": [
    [
      1.2064881739956153,
      0.0,
      0.0
    ],
    [
      0.0,
      1.2064881739956153,
      0.0
    ],
    [
      0.0,
      0.0,
      0.32832552686669664
    ]
  ],
  "seekpath_primitive_lattice_A": [
    [
      9.56853,
      -2.603915,
      0.0
    ],
    [
      9.56853,
      2.603915,
      0.0
    ],
    [
      0.0,
      0.0,
      5.20783
    ]
  ],
  "seekpath_reciprocal_lattice_Ainv_2pi": [
    [
      0.32832552686669664,
      -1.2064881739956153,
      0.0
    ],
    [
      0.32832552686669664,
      1.2064881739956153,
      0.0
    ],
    [
      0.0,
      0.0,
      1.2064881739956153
    ]
  ],
  "bz_basis": "SeeK-path standardized primitive reciprocal basis",
  "point_source": "fully_manual",
  "manual_coordinate_basis": "input",
  "seekpath_point_coords_reduced": {
    "GAMMA": [
      0.0,
      0.0,
      0.0
    ],
    "Y": [
      0.5,
      0.5,
      0.0
    ],
    "T": [
      0.5,
      0.5,
      0.5
    ],
    "T_2": [
      0.5,
      0.5,
      -0.5
    ],
    "Z": [
      0.0,
      0.0,
      0.5
    ],
    "Z_2": [
      0.0,
      0.0,
      -0.5
    ],
    "S": [
      0.0,
      0.5,
      0.0
    ],
    "R": [
      0.0,
      0.5,
      0.5
    ],
    "R_2": [
      0.0,
      0.5,
      -0.5
    ],
    "DELTA_0": [
      -0.26851412406948166,
      0.26851412406948166,
      0.0
    ],
    "F_0": [
      0.26851412406948166,
      0.7314858759305183,
      0.0
    ],
    "B_0": [
      -0.26851412406948166,
      0.26851412406948166,
      0.5
    ],
    "B_2": [
      -0.26851412406948166,
      0.26851412406948166,
      -0.5
    ],
    "G_0": [
      0.26851412406948166,
      0.7314858759305183,
      0.5
    ],
    "G_2": [
      0.26851412406948166,
      0.7314858759305183,
      -0.5
    ]
  },
  "manual_point_coords_reduced": {
    "X": [
      0.5,
      0.0,
      0.0
    ],
    "\u0393": [
      0.0,
      0.0,
      0.0
    ],
    "Y": [
      0.0,
      0.5,
      0.0
    ],
    "R": [
      0.5,
      0.0,
      0.5
    ],
    "R'": [
      0.5,
      0.0,
      -0.5
    ]
  },
  "point_coords_cartesian_Ainv": {
    "X": [
      0.6032440869978076,
      0.0,
      0.0
    ],
    "\u0393": [
      0.0,
      0.0,
      0.0
    ],
    "Y": [
      0.0,
      0.6032440869978076,
      0.0
    ],
    "R": [
      0.6032440869978076,
      0.0,
      0.16416276343334832
    ],
    "R'": [
      0.6032440869978076,
      0.0,
      -0.16416276343334832
    ]
  },
  "path_sequences": [
    [
      "X",
      "\u0393",
      "Y",
      "\u0393",
      "R",
      "\u0393",
      "R'"
    ]
  ],
  "seekpath_raw": {
    "point_coords": {
      "GAMMA": [
        0.0,
        0.0,
        0.0
      ],
      "Y": [
        0.5,
        0.5,
        0.0
      ],
      "T": [
        0.5,
        0.5,
        0.5
      ],
      "T_2": [
        0.5,
        0.5,
        -0.5
      ],
      "Z": [
        0.0,
        0.0,
        0.5
      ],
      "Z_2": [
        0.0,
        0.0,
        -0.5
      ],
      "S": [
        0.0,
        0.5,
        0.0
      ],
      "R": [
        0.0,
        0.5,
        0.5
      ],
      "R_2": [
        0.0,
        0.5,
        -0.5
      ],
      "DELTA_0": [
        -0.26851412406948166,
        0.26851412406948166,
        0.0
      ],
      "F_0": [
        0.26851412406948166,
        0.7314858759305183,
        0.0
      ],
      "B_0": [
        -0.26851412406948166,
        0.26851412406948166,
        0.5
      ],
      "B_2": [
        -0.26851412406948166,
        0.26851412406948166,
        -0.5
      ],
      "G_0": [
        0.26851412406948166,
        0.7314858759305183,
        0.5
      ],
      "G_2": [
        0.26851412406948166,
        0.7314858759305183,
        -0.5
      ]
    },
    "path": [
      [
        "GAMMA",
        "Y"
      ],
      [
        "Y",
        "F_0"
      ],
      [
        "DELTA_0",
        "GAMMA"
      ],
      [
        "GAMMA",
        "Z"
      ],
      [
        "Z",
        "B_0"
      ],
      [
        "G_0",
        "T"
      ],
      [
        "T",
        "Y"
      ],
      [
        "GAMMA",
        "S"
      ],
      [
        "S",
        "R"
      ],
      [
        "R",
        "Z"
      ],
      [
        "Z",
        "T"
      ]
    ],
    "has_inversion_symmetry": false,
    "augmented_path": false,
    "bravais_lattice": "oC",
    "bravais_lattice_extended": "oC2",
    "conv_lattice": [
      [
        19.13706,
        0.0,
        0.0
      ],
      [
        0.0,
        5.20783,
        0.0
      ],
      [
        0.0,
        0.0,
        5.20783
      ]
    ],
    "conv_positions": [
      [
        0.4007499999999999,
        0.25097999999999976,
        0.25904000000000016
      ],
      [
        0.09925000000000012,
        0.7509799999999998,
        0.25904000000000016
      ],
      [
        0.4007499999999999,
        0.7490200000000002,
        0.7590400000000002
      ],
      [
        0.09925000000000012,
        0.24902000000000024,
        0.7590400000000002
      ],
      [
        0.0,
        0.2528999999999999,
        0.25904000000000016
      ],
      [
        0.0,
        0.7471000000000001,
        0.7590400000000002
      ],
      [
        0.3155399999999999,
        0.7555199999999997,
        0.25904000000000016
      ],
      [
        0.18446000000000012,
        0.25551999999999975,
        0.25904000000000016
      ],
      [
        0.3155399999999999,
        0.24448000000000025,
        0.7590400000000002
      ],
      [
        0.18446000000000012,
        0.7444800000000003,
        0.7590400000000002
      ],
      [
        0.0,
        0.7499999999999998,
        0.25904000000000016
      ],
      [
        0.0,
        0.2500000000000002,
        0.7590400000000002
      ],
      [
        0.19761999999999988,
        0.7089799999999999,
        0.25904000000000016
      ],
      [
        0.3023800000000001,
        0.20897999999999994,
        0.25904000000000016
      ],
      [
        0.19761999999999988,
        0.29102000000000006,
        0.7590400000000002
      ],
      [
        0.3023800000000001,
        0.7910200000000001,
        0.7590400000000002
      ],
      [
        0.08731999999999986,
        0.5378699999999998,
        0.97137
      ],
      [
        0.41268000000000016,
        0.03786999999999985,
        0.97137
      ],
      [
        0.08731999999999986,
        0.46213000000000015,
        0.47136999999999984
      ],
      [
        0.41268000000000016,
        0.9621300000000002,
        0.47136999999999984
      ],
      [
        0.1085499999999999,
        0.9621299999999999,
        0.54671
      ],
      [
        0.3914500000000001,
        0.46212999999999993,
        0.54671
      ],
      [
        0.1085499999999999,
        0.03787000000000007,
        0.04671000000000003
      ],
      [
        0.3914500000000001,
        0.5378700000000001,
        0.04671000000000003
      ],
      [
        0.9007499999999999,
        0.7509799999999998,
        0.25904000000000016
      ],
      [
        0.5992500000000001,
        0.25097999999999976,
        0.25904000000000016
      ],
      [
        0.9007499999999999,
        0.24902000000000024,
        0.7590400000000002
      ],
      [
        0.5992500000000001,
        0.7490200000000002,
        0.7590400000000002
      ],
      [
        0.5,
        0.7528999999999999,
        0.25904000000000016
      ],
      [
        0.5,
        0.2471000000000001,
        0.7590400000000002
      ],
      [
        0.8155399999999999,
        0.25551999999999975,
        0.25904000000000016
      ],
      [
        0.6844600000000001,
        0.7555199999999997,
        0.25904000000000016
      ],
      [
        0.8155399999999999,
        0.7444800000000003,
        0.7590400000000002
      ],
      [
        0.6844600000000001,
        0.24448000000000025,
        0.7590400000000002
      ],
      [
        0.5,
        0.24999999999999978,
        0.25904000000000016
      ],
      [
        0.5,
        0.7500000000000002,
        0.7590400000000002
      ],
      [
        0.6976199999999999,
        0.20897999999999994,
        0.25904000000000016
      ],
      [
        0.8023800000000001,
        0.7089799999999999,
        0.25904000000000016
      ],
      [
        0.6976199999999999,
        0.7910200000000001,
        0.7590400000000002
      ],
      [
        0.8023800000000001,
        0.29102000000000006,
        0.7590400000000002
      ],
      [
        0.5873199999999998,
        0.03786999999999985,
        0.97137
      ],
      [
        0.9126800000000002,
        0.5378699999999998,
        0.97137
      ],
      [
        0.5873199999999998,
        0.9621300000000002,
        0.47136999999999984
      ],
      [
        0.9126800000000002,
        0.46213000000000015,
        0.47136999999999984
      ],
      [
        0.6085499999999999,
        0.46212999999999993,
        0.54671
      ],
      [
        0.8914500000000001,
        0.9621299999999999,
        0.54671
      ],
      [
        0.6085499999999999,
        0.5378700000000001,
        0.04671000000000003
      ],
      [
        0.8914500000000001,
        0.03787000000000007,
        0.04671000000000003
      ]
    ],
    "conv_types": [
      25,
      25,
      25,
      25,
      20,
      20,
      20,
      20,
      20,
      20,
      8,
      8,
      8,
      8,
      8,
      8,
      8,
      8,
      8,
      8,
      8,
      8,
      8,
      8,
      25,
      25,
      25,
      25,
      20,
      20,
      20,
      20,
      20,
      20,
      8,
      8,
      8,
      8,
      8,
      8,
      8,
      8,
      8,
      8,
      8,
      8,
      8,
      8
    ],
    "primitive_lattice": [
      [
        9.56853,
        -2.603915,
        0.0
      ],
      [
        9.56853,
        2.603915,
        0.0
      ],
      [
        0.0,
        0.0,
        5.20783
      ]
    ],
    "primitive_positions": [
      [
        0.14977000000000013,
        0.6517299999999997,
        0.25904000000000016
      ],
      [
        -0.6517299999999997,
        0.8502299999999998,
        0.25904000000000016
      ],
      [
        -0.34827000000000036,
        1.1497700000000002,
        0.7590400000000002
      ],
      [
        -0.14977000000000013,
        0.34827000000000036,
        0.7590400000000002
      ],
      [
        -0.2528999999999999,
        0.2528999999999999,
        0.25904000000000016
      ],
      [
        -0.7471000000000001,
        0.7471000000000001,
        0.7590400000000002
      ],
      [
        -0.43997999999999987,
        1.0710599999999997,
        0.25904000000000016
      ],
      [
        -0.07105999999999962,
        0.43997999999999987,
        0.25904000000000016
      ],
      [
        0.07105999999999962,
        0.5600200000000002,
        0.7590400000000002
      ],
      [
        -0.5600200000000002,
        0.9289400000000003,
        0.7590400000000002
      ],
      [
        -0.7499999999999998,
        0.7499999999999998,
        0.25904000000000016
      ],
      [
        -0.2500000000000002,
        0.2500000000000002,
        0.7590400000000002
      ],
      [
        -0.51136,
        0.9065999999999999,
        0.25904000000000016
      ],
      [
        0.09340000000000015,
        0.51136,
        0.25904000000000016
      ],
      [
        -0.09340000000000018,
        0.48863999999999996,
        0.7590400000000002
      ],
      [
        -0.48863999999999996,
        1.0934000000000001,
        0.7590400000000002
      ],
      [
        -0.45055,
        0.6251899999999997,
        0.97137
      ],
      [
        0.3748100000000003,
        0.45055,
        0.97137
      ],
      [
        -0.3748100000000003,
        0.54945,
        0.47136999999999984
      ],
      [
        -0.54945,
        1.3748100000000003,
        0.47136999999999984
      ],
      [
        -0.85358,
        1.0706799999999999,
        0.54671
      ],
      [
        -0.07067999999999985,
        0.85358,
        0.54671
      ],
      [
        0.07067999999999983,
        0.14641999999999997,
        0.04671000000000003
      ],
      [
        -0.14642,
        0.9293200000000001,
        0.04671000000000003
      ]
    ],
    "primitive_types": [
      25,
      25,
      25,
      25,
      20,
      20,
      20,
      20,
      20,
      20,
      8,
      8,
      8,
      8,
      8,
      8,
      8,
      8,
      8,
      8,
      8,
      8,
      8,
      8
    ],
    "reciprocal_primitive_lattice": [
      [
        0.32832552686669664,
        -1.2064881739956153,
        0.0
      ],
      [
        0.32832552686669664,
        1.2064881739956153,
        0.0
      ],
      [
        0.0,
        0.0,
        1.2064881739956153
      ]
    ],
    "inverse_primitive_transformation_matrix": [
      [
        1,
        -1,
        0
      ],
      [
        1,
        1,
        0
      ],
      [
        0,
        0,
        1
      ]
    ],
    "primitive_transformation_matrix": [
      [
        0.5,
        0.5,
        0.0
      ],
      [
        -0.5,
        0.5,
        0.0
      ],
      [
        0.0,
        0.0,
        1.0
      ]
    ],
    "volume_original_wrt_conv": 0.9999999999999997,
    "volume_original_wrt_prim": 1.9999999999999993,
    "spacegroup_number": 36,
    "spacegroup_international": "Cmc2_1",
    "rotation_matrix": [
      [
        0.0,
        0.0,
        1.0
      ],
      [
        0.0,
        1.0,
        0.0
      ],
      [
        -1.0,
        0.0,
        0.0
      ]
    ]
  }
}